LICENSE
README.md
setup.cfg
setup.py
lasertools_trace/__init__.py
lasertools_trace/trace_model.py
lasertools_trace.egg-info/PKG-INFO
lasertools_trace.egg-info/SOURCES.txt
lasertools_trace.egg-info/dependency_links.txt
lasertools_trace.egg-info/requires.txt
lasertools_trace.egg-info/top_level.txt
lasertools_trace/models/__init__.py
lasertools_trace/models/base.py
lasertools_trace/models/dscan.py
lasertools_trace/models/frog_sd.py
lasertools_trace/models/frog_shg.py